arcu/arcu.py
arcu-0.1.1.dist-info/LICENSE
arcu-0.1.1.dist-info/METADATA
arcu-0.1.1.dist-info/WHEEL
arcu-0.1.1.dist-info/top_level.txt
arcu-0.1.1.dist-info/RECORD
