Metadata-Version: 2.1
Name: arcu
Version: 0.1.1
Summary: Find representative subpopulations in single cell imaging data.
Home-page: https://github.com/harrismdavis/arcu
Author: Harris Davis
Author-email: harris.davis@outlook.com
License: MIT
Keywords: image analysis,single-cell bioinformatics,computational biology
Platform: UNKNOWN
Classifier: Development Status :: 3 - Alpha
Classifier: Intended Audience :: Science/Research
Classifier: Topic :: Scientific/Engineering :: Bio-Informatics
Classifier: License :: OSI Approved :: MIT License
Classifier: Programming Language :: Python :: 3.6
Classifier: Programming Language :: Python :: 3.7
Classifier: Programming Language :: Python :: 3.8
Classifier: Programming Language :: Python :: 3.9
Classifier: Operating System :: OS Independent
Requires-Python: >=3.6
Requires-Dist: numpy (>=1.22.4)
Requires-Dist: pandas (>=1.3.2)
